{
    "exportDeDonnees": {
        "etablissementCode": "0750663N",
        "modeleCode": 42807,
        "exportCandidats": [
            {
                "formationCode": 8994,
                "candidats": [
                    {
                        "DonneesCandidats": {
                            "NumeroDossierCandidat": 163611,
                            "NomCandidat": "PASDELOUP",
                            "PrenomCandidat": "Saphia",
                            "DateNaissance": "22/01/2008"
                        },
                        "Scolarite": [
                            {
                                "AnneeScolaireLibelle": "2024-2025",
                                "ScolariteFrancaiseLibelle": "Scolarité française",
                                "NiveauEtudeLibelle": "Terminale",
                                "TypeFormationLibelle": "Terminale",
                                "TypeClasseLibelle": "Générale",
                                "TypeEtablissementorigineLibelle": "Lycée général et technologique",
                                "NomEtablissementOrigine": "Lycée Camille Claudel",
                                "CommuneEtablissementOrigineLibelle": "Vauréal",
                                "PaysEtablissementorigineLibelle": "France"
                            },
                            {
                                "ScolariteFrancaiseLibelle": "Scolarité française"
                            }
                        ],
                        "BulletinsScolaires": [
                            {
                                "AnneeLibelle": "2024-2025",
                                "BulletinsScolairesAnnee": {
                                    "SerieLibelle": "Série Générale",
                                    "BulletinsScolairesSeries": [
                                        {
                                            "TrimestreLibelle": "Second trimestre",
                                            "BulletinsScolairesParPeriode": [
                                                {
                                                    "MatiereBulletinLibelle": "Mathématiques Spécialité",
                                                    "MoyenneduCandidat": "13,70",
                                                    "MoyenneclasseCandidat": "10,77",
                                                    "MoyenneBasseClasseduCandidat": "3,70",
                                                    "MoyenneHauteClasseduCandidat": "19,40",
                                                    "TypedeSaisieCode": 1,
                                                    "AppreciationProfesseur": "Un ensemble satisfaisant et en net progrès. Le travail a gagné en exigence et en profondeur mettant en exergue d'indéniables qualités de réflexion. La participation est vive et pertinente. Il convient cependant de gagner en rigueur dans vos travaux écrits; la mise en forme de votre argumentation ternie parfois la qualité du fond. Travaillez cette rigueur en vous employant à une maîtrise experte des applications du cours. Mes plus vifs compliments pour vos résultats et votre implication dans le travail."
                                                },
                                                {
                                                    "MatiereBulletinLibelle": "Langue vivante A",
                                                    "MoyenneduCandidat": "18,25",
                                                    "MoyenneclasseCandidat": "14,97",
                                                    "MoyenneBasseClasseduCandidat": "9,00",
                                                    "MoyenneHauteClasseduCandidat": "18,50",
                                                    "TypedeSaisieCode": 1,
                                                    "AppreciationProfesseur": "A nouveau un excellent bilan, tant dans l'attitude, toujours volontaire, que dans le travail. Le niveau est solide dans la matière. Félicitations !"
                                                },
                                                {
                                                    "MatiereBulletinLibelle": "Philosophie",
                                                    "MoyenneduCandidat": "14,00",
                                                    "MoyenneclasseCandidat": "13,87",
                                                    "MoyenneBasseClasseduCandidat": "11,17",
                                                    "MoyenneHauteClasseduCandidat": "16,00",
                                                    "TypedeSaisieCode": 1,
                                                    "AppreciationProfesseur": "Un trimestre très satisfaisant et très encourageant. Des progrès significatifs ont été accomplis et votre écrit a gagné en précision. Toujours beaucoup de sérieux. Continuez ainsi en maintenant vos efforts pour développer votre écrit."
                                                },
                                                {
                                                    "MatiereBulletinLibelle": "Sciences de la vie et de la Terre Spécialité",
                                                    "MoyenneduCandidat": "16,10",
                                                    "MoyenneclasseCandidat": "14,12",
                                                    "MoyenneBasseClasseduCandidat": "8,80",
                                                    "MoyenneHauteClasseduCandidat": "19,00",
                                                    "TypedeSaisieCode": 1,
                                                    "AppreciationProfesseur": "Un très bon trimestre, aux résultats solides et réguliers. La participation en classe est toujours très intelligente, et participe à la dynamique de classe. Bravo ! Continuez ainsi."
                                                }
                                            ]
                                        },
                                        {
                                            "TrimestreLibelle": "Premier trimestre",
                                            "BulletinsScolairesParPeriode": [
                                                {
                                                    "MatiereBulletinLibelle": "Mathématiques Spécialité",
                                                    "MoyenneduCandidat": "10,00",
                                                    "MoyenneclasseCandidat": "10,25",
                                                    "MoyenneBasseClasseduCandidat": "2,50",
                                                    "MoyenneHauteClasseduCandidat": "17,50",
                                                    "TypedeSaisieCode": 1,
                                                    "AppreciationProfesseur": "Un ensemble fragile masquant quelques irrégularités dans les résultats. La pertinence des réflexions témoigne de qualités évidentes d'analyse et de réflexion. Il convient de les mettre davantage en relief, dans le passage à l'écrit, en accompagnant votre argumentation par une rédaction précise et rigoureuse. Un travail systématique et encore plus profondeur des applications fondamentales du cahier de cours vous fera gagner en rigueur et en automatisme. Elément moteur pour le groupe."
                                                },
                                                {
                                                    "MatiereBulletinLibelle": "Sciences de la vie et de la Terre Spécialité",
                                                    "MoyenneduCandidat": "16,50",
                                                    "MoyenneclasseCandidat": "12,22",
                                                    "MoyenneBasseClasseduCandidat": "8,50",
                                                    "MoyenneHauteClasseduCandidat": "19,10",
                                                    "TypedeSaisieCode": 1,
                                                    "AppreciationProfesseur": "Un excellent trimestre. Sérieux des rendus et participation extrêmement intéressante sont toujours au rendez-vous. Continuez ainsi !"
                                                },
                                                {
                                                    "MatiereBulletinLibelle": "Philosophie",
                                                    "MoyenneduCandidat": "14,00",
                                                    "MoyenneclasseCandidat": "13,66",
                                                    "MoyenneBasseClasseduCandidat": "11,75",
                                                    "MoyenneHauteClasseduCandidat": "16,00",
                                                    "TypedeSaisieCode": 1,
                                                    "AppreciationProfesseur": "Un trimestre très satisfaisant. Beaucoup de sérieux et d'attention. Une grande application dans les activités de classe. Une participation active à l'oral. Continuez dans cette voie."
                                                },
                                                {
                                                    "MatiereBulletinLibelle": "Langue vivante A",
                                                    "MoyenneduCandidat": "17,50",
                                                    "MoyenneclasseCandidat": "14,97",
                                                    "MoyenneBasseClasseduCandidat": "9,00",
                                                    "MoyenneHauteClasseduCandidat": "18,56",
                                                    "TypedeSaisieCode": 1,
                                                    "AppreciationProfesseur": "Un excellent premier trimestre, votre souci de bien faire et votre dynamisme contribuent au bon déroulement des cours. Félicitations !"
                                                }
                                            ]
                                        }
                                    ]
                                }
                            },
                            {
                                "AnneeLibelle": "2023-2024",
                                "BulletinsScolairesAnnee": {
                                    "SerieLibelle": "Série Générale",
                                    "BulletinsScolairesSeries": [
                                        {
                                            "TrimestreLibelle": "Premier semestre",
                                            "BulletinsScolairesParPeriode": [
                                                {
                                                    "MatiereBulletinLibelle": "Sciences de la vie et de la Terre Spécialité",
                                                    "MoyenneduCandidat": "15,01",
                                                    "MoyenneclasseCandidat": "12,36",
                                                    "MoyenneBasseClasseduCandidat": "8,38",
                                                    "MoyenneHauteClasseduCandidat": "18,98",
                                                    "TypedeSaisieCode": 1,
                                                    "AppreciationProfesseur": "Une bonne évolution au cours de ce semestre, avec une attitude de plus en plus sérieuse ce qu'il lui a permis de trouver un rythme de travail toujours plus efficace. Il faut poursuivre ainsi c'est très positif."
                                                },
                                                {
                                                    "MatiereBulletinLibelle": "Physique-Chimie Spécialité",
                                                    "MoyenneduCandidat": "12,60",
                                                    "MoyenneclasseCandidat": "12,98",
                                                    "MoyenneBasseClasseduCandidat": "7,40",
                                                    "MoyenneHauteClasseduCandidat": "18,30",
                                                    "TypedeSaisieCode": 1,
                                                    "AppreciationProfesseur": "Un semestre assez satisfaisant. Le travail est sérieux."
                                                },
                                                {
                                                    "MatiereBulletinLibelle": "Mathématiques Spécialité",
                                                    "MoyenneduCandidat": "13,71",
                                                    "MoyenneclasseCandidat": "12,45",
                                                    "MoyenneBasseClasseduCandidat": "3,00",
                                                    "MoyenneHauteClasseduCandidat": "19,50",
                                                    "TypedeSaisieCode": 1,
                                                    "AppreciationProfesseur": "En progression. Bilan positif. Continuer ainsi Saphia."
                                                },
                                                {
                                                    "MatiereBulletinLibelle": "Langue vivante A",
                                                    "MoyenneduCandidat": "18,57",
                                                    "MoyenneclasseCandidat": "13,41",
                                                    "MoyenneBasseClasseduCandidat": "8,38",
                                                    "MoyenneHauteClasseduCandidat": "18,67",
                                                    "TypedeSaisieCode": 1,
                                                    "AppreciationProfesseur": "Résultats réguliers et très satisfaisants, excellente participation, continuez ainsi."
                                                },
                                                {
                                                    "MatiereBulletinLibelle": "Français",
                                                    "MoyenneduCandidat": "11,00",
                                                    "MoyenneclasseCandidat": "9,55",
                                                    "MoyenneBasseClasseduCandidat": "3,50",
                                                    "MoyenneHauteClasseduCandidat": "18,50",
                                                    "TypedeSaisieCode": 1,
                                                    "AppreciationProfesseur": "Semestre convenable. Les méthodes de dissertation et de commentaire sont en place mais elles doivent consolidées. Forte participation à l'oral et un intérêt manifeste pour la matière. Mettez à profit le second semestre pour améliorer vos résultats."
                                                }
                                            ]
                                        },
                                        {
                                            "TrimestreLibelle": "Second semestre",
                                            "BulletinsScolairesParPeriode": [
                                                {
                                                    "MatiereBulletinLibelle": "Langue vivante A",
                                                    "MoyenneduCandidat": "18,67",
                                                    "MoyenneclasseCandidat": "12,96",
                                                    "MoyenneBasseClasseduCandidat": "7,33",
                                                    "MoyenneHauteClasseduCandidat": "18,67",
                                                    "TypedeSaisieCode": 1,
                                                    "AppreciationProfesseur": "Ensemble très satisfaisant, beaucoup de sérieux, excellente participation, bravo à vous !"
                                                },
                                                {
                                                    "MatiereBulletinLibelle": "Français",
                                                    "MoyenneduCandidat": "15,17",
                                                    "MoyenneclasseCandidat": "11,28",
                                                    "MoyenneBasseClasseduCandidat": "6,42",
                                                    "MoyenneHauteClasseduCandidat": "16,80",
                                                    "TypedeSaisieCode": 1,
                                                    "AppreciationProfesseur": "Un ensemble annuel satisfaisant et fort avec une forte progression des résultats. Les méthodes sont en place. Vous êtes prête. Bravo pour cette année."
                                                },
                                                {
                                                    "MatiereBulletinLibelle": "Sciences de la vie et de la Terre Spécialité",
                                                    "MoyenneduCandidat": "12,87",
                                                    "MoyenneclasseCandidat": "13,01",
                                                    "MoyenneBasseClasseduCandidat": "9,41",
                                                    "MoyenneHauteClasseduCandidat": "17,04",
                                                    "TypedeSaisieCode": 1,
                                                    "AppreciationProfesseur": "Un bon semestre une nouvelle fois. Plus sérieux que le premier avec une implication bien marquée et remarquée. Il faut poursuivre ces efforts et encore les accentuer pour la rentrée prochaine."
                                                },
                                                {
                                                    "MatiereBulletinLibelle": "Mathématiques Spécialité",
                                                    "MoyenneduCandidat": "15,00",
                                                    "MoyenneclasseCandidat": "15,87",
                                                    "MoyenneBasseClasseduCandidat": "11,40",
                                                    "MoyenneHauteClasseduCandidat": "20,00",
                                                    "TypedeSaisieCode": 1,
                                                    "AppreciationProfesseur": "Résultats corrects. Relâchement en fin de semestre."
                                                },
                                                {
                                                    "MatiereBulletinLibelle": "Physique-Chimie Spécialité",
                                                    "MoyenneduCandidat": "10,80",
                                                    "MoyenneclasseCandidat": "12,29",
                                                    "MoyenneBasseClasseduCandidat": "5,30",
                                                    "MoyenneHauteClasseduCandidat": "18,80",
                                                    "TypedeSaisieCode": 1,
                                                    "AppreciationProfesseur": "Le bilan reste correct ce semestre."
                                                }
                                            ]
                                        }
                                    ]
                                }
                            }
                        ],
                        "FicheAvenir": {
                            "NiveauClasseCode": 5
                        },
                        "AppreciationsEnseignantsFicheAvenir": [
                            {
                                "MatiereFicheAvenirLibelle": "Philosophie",
                                "MatiereFicheAvenirLibelleBCN": "PHILOSOPHIE",
                                "AppreciationFicheAvenir": "Travail et résultats satisfaisants."
                            },
                            {
                                "MatiereFicheAvenirLibelle": "Langue vivante A",
                                "MatiereFicheAvenirLibelleBCN": "LANGUE VIVANTE 1",
                                "AppreciationFicheAvenir": "Excellent bilan, participation orale dynamique et compétences solidement maîtrisées dans la matière."
                            },
                            {
                                "MatiereFicheAvenirLibelle": "Mathématiques Spécialité",
                                "MatiereFicheAvenirLibelleBCN": "MATHEMATIQUES",
                                "AppreciationFicheAvenir": "Un ensemble convenable et en progrès, récompense légitime d'un travail sérieux et dynamique permettant de donner davantage de relief à des qualités d'analyse et de réflexion. Une singularité dans la réflexion qu'il convient de garder et de nourrir par une approche encore plus rigoureuse dans l'argumentation. Une très belle maturité dans les apprentissages et des acquis solides, tant du point de vue des savoirs que des savoirs faire; ils constituent de sérieux atouts pour réussir et s'épanouir dans le supérieur."
                            },
                            {
                                "MatiereFicheAvenirLibelle": "Sciences de la vie et de la Terre Spécialité",
                                "MatiereFicheAvenirLibelleBCN": "SCIENCES DE LA VIE ET DE LA TERRE",
                                "AppreciationFicheAvenir": "D'excellents résultats, qui ont été tout au long de ces deux trimestre, solides et homogènes. Un réelle appétence pour la matière a permis une acquisition de la méthode  rapide et efficace !"
                            }
                        ],
                        "Baccalaureat": {
                            "EDSScolaritePremiere1LibelleBCN": "MATHEMATIQUES",
                            "EDSScolaritePremiere2LibelleBCN": "PHYSIQUE-CHIMIE",
                            "EDSScolaritePremiere3LibelleBCN": "SCIENCES DE LA VIE ET DE LA TERRE",
                            "EDSScolariteTerminale1Libelle": "Mathématiques Spécialité",
                            "EDSScolariteTerminale2Libelle": "Sciences de la vie et de la Terre Spécialité",
                            "EDSScolaritePremiere1Libelle": "Mathématiques Spécialité",
                            "EDSScolaritePremiere2Libelle": "Physique-Chimie Spécialité",
                            "EDSScolaritePremiere3Libelle": "Sciences de la vie et de la Terre Spécialité"
                        },
                        "NotesBaccalaureat": [
                            {
                                "EpreuveLibelle": "Mathématiques"
                            },
                            {
                                "EpreuveLibelle": "Sciences de la Vie et de la Terre"
                            },
                            {
                                "EpreuveLibelle": "Français écrit",
                                "NoteEpreuve": "11,0"
                            },
                            {
                                "EpreuveLibelle": "Français oral",
                                "NoteEpreuve": "18,0"
                            },
                            {
                                "EpreuveLibelle": "Physique-Chimie  (EDS suivi uniquement en 1ère)",
                                "NoteEpreuve": "11,7"
                            }
                        ]
                    }
                ]
            }
        ]
    },
    "Code candidat": "163611",
    "Groupe algorithmique": "C",
    "Classement Algorithmique": "1292",
    "Remarques": "excellence(5) - notesSC : 13 - NotesFR : 15- Notes Bac :13 - Bonus rang :3",
    "Spe": "Tle :M - SVT -  1ere - PC",
    "candidat précédent": "163606",
    "candidat suivant": "167044",
    "lettre": "Madame, Monsieur,<br /> Actuellement en terminale scientifique, je vous adresse ma candidature pour la classe préparatoire scientifique BCPST du lycée Chaptal. Attirée par les sciences naturelles et particulièrement par la biologie, je suis convaincu que l'excellence académique et l'encadrement de qualité offerts par votre établissement sont les éléments indispensables à la réalisation de mon projet.<br /> Lors de ma visite au lycée Chaptal, j'ai eu l'opportunité de rencontrer des étudiants de la prépa et de discuter avec eux de leur expérience. Leur enthousiasme, ainsi que les résultats impressionnants obtenus par vos élèves lors des concours, ont renforcé ma volonté de rejoindre votre établissement. J'ai également été marqué par la convivialité de l'environnement, malgré la rigueur académique. Cette atmosphère d'exception serait un cadre idéal pour mon épanouissement.<br /> Je vous remercie pour l'attention que vous porterez à ma candidature et reste à votre disposition pour tout renseignement complémentaire.<br /> Veuillez agréer, Madame, Monsieur, l'expression de mes salutations respectueuses.",
    "veto": "False",
    "geol": "False"
}