{
  "DonneesCandidats": {
    "NumeroDossierCandidat": 614245,
    "NomCandidat": "DE LA CROIX",
    "PrenomCandidat": "Gabrielle",
    "DateNaissance": "01/07/2008"
  },
  "Scolarite": [
    {
      "AnneeScolaireLibelle": "2025-2026",
      "ScolariteFrancaiseLibelle": "Scolarité française",
      "NiveauEtudeLibelle": "Terminale",
      "TypeFormationLibelle": "Terminale",
      "TypeClasseLibelle": "Générale",
      "TypeEtablissementorigineLibelle": "Lycée général et technologique",
      "NomEtablissementOrigine": "Lycée SAINT JEAN HULST",
      "CommuneEtablissementOrigineLibelle": "Versailles",
      "PaysEtablissementorigineLibelle": "France"
    },
    {
      "ScolariteFrancaiseLibelle": "Scolarité française"
    }
  ],
  "BulletinsScolaires": [
    {
      "AnneeLibelle": "2024-2025",
      "BulletinsScolairesAnnee": {
        "SerieLibelle": "Série Générale",
        "BulletinsScolairesSeries": [
          {
            "TrimestreLibelle": "Second trimestre",
            "BulletinsScolairesParPeriode": [
              {
                "MatiereBulletinLibelle": "Français",
                "MoyenneduCandidat": "13,97",
                "MoyenneclasseCandidat": "12,83",
                "MoyenneBasseClasseduCandidat": "8,21",
                "MoyenneHauteClasseduCandidat": "15,97",
                "TypedeSaisieCode": 1,
                "AppreciationProfesseur": "Une petite baisse dans les résultats ce trimestre malgré un travail qui reste sérieux. Gabrielle doit prendre plus de recul sur les oeuvres présentées afin de gagner en fluidité à l'oral ; l'écrit est structuré mais l'argumentation doit être plus rigoureuse."
              },
              {
                "MatiereBulletinLibelle": "Physique-Chimie Spécialité",
                "MoyenneduCandidat": "12,09",
                "MoyenneclasseCandidat": "11,34",
                "MoyenneBasseClasseduCandidat": "6,71",
                "MoyenneHauteClasseduCandidat": "16,30",
                "TypedeSaisieCode": 1,
                "AppreciationProfesseur": "Les progrès consolident un assez bon ensemble. Continuez ainsi."
              },
              {
                "MatiereBulletinLibelle": "Langue vivante A",
                "MoyenneduCandidat": "16,83",
                "MoyenneclasseCandidat": "14,27",
                "MoyenneBasseClasseduCandidat": "10,79",
                "MoyenneHauteClasseduCandidat": "18,69",
                "TypedeSaisieCode": 1,
                "AppreciationProfesseur": "Très bon travail, tant à l'écrit qu'à l'oral. N'hésitez pas à participer plus régulièrement pour viser l'excellence !"
              },
              {
                "MatiereBulletinLibelle": "Sciences de la vie et de la Terre Spécialité",
                "MoyenneduCandidat": "14,25",
                "MoyenneclasseCandidat": "13,19",
                "MoyenneBasseClasseduCandidat": "4,33",
                "MoyenneHauteClasseduCandidat": "19,00",
                "TypedeSaisieCode": 1,
                "AppreciationProfesseur": "Bon trimestre dans l'ensemble : le travail est sérieux, poursuivez ainsi !"
              },
              {
                "MatiereBulletinLibelle": "Mathématiques Spécialité",
                "MoyenneduCandidat": "12,47",
                "MoyenneclasseCandidat": "11,53",
                "MoyenneBasseClasseduCandidat": "3,78",
                "MoyenneHauteClasseduCandidat": "18,53",
                "TypedeSaisieCode": 1,
                "AppreciationProfesseur": "De beaux progrès ce trimestre, fruits de votre investissement sans faille. Poursuivez de la sorte afin de consolider l'ensemble et de gagner en efficacité."
              }
            ]
          },
          {
            "TrimestreLibelle": "Troisième trimestre",
            "BulletinsScolairesParPeriode": [
              {
                "MatiereBulletinLibelle": "Langue vivante A",
                "MoyenneduCandidat": "17,33",
                "MoyenneclasseCandidat": "14,27",
                "MoyenneBasseClasseduCandidat": "9,80",
                "MoyenneHauteClasseduCandidat": "19,23",
                "TypedeSaisieCode": 1,
                "AppreciationProfesseur": "Très bon trimestre. Gabrielle a fait preuve de sérieux dans le travail écrit. Il faudra équilibrer ce bon niveau de langue avec un investissement plus régulier en classe."
              },
              {
                "MatiereBulletinLibelle": "Sciences de la vie et de la Terre Spécialité",
                "MoyenneduCandidat": "16,82",
                "MoyenneclasseCandidat": "14,95",
                "MoyenneBasseClasseduCandidat": "6,59",
                "MoyenneHauteClasseduCandidat": "19,68",
                "TypedeSaisieCode": 1,
                "AppreciationProfesseur": "Très bon trimestre : le travail a été régulier et méthodique. Bravo !"
              },
              {
                "MatiereBulletinLibelle": "Français",
                "MoyenneduCandidat": "13,14",
                "MoyenneclasseCandidat": "12,80",
                "MoyenneBasseClasseduCandidat": "7,61",
                "MoyenneHauteClasseduCandidat": "16,71",
                "TypedeSaisieCode": 1,
                "AppreciationProfesseur": "Un ensemble assez satisfaisant malgré une légère baisse dans les résultats. L'oral est de bonne qualité. A l'écrit, le commentaire reste trop superficiel ; la dissertation est mieux maîtrisée."
              },
              {
                "MatiereBulletinLibelle": "Mathématiques Spécialité",
                "MoyenneduCandidat": "12,25",
                "MoyenneclasseCandidat": "12,35",
                "MoyenneBasseClasseduCandidat": "6,21",
                "MoyenneHauteClasseduCandidat": "19,15",
                "TypedeSaisieCode": 1,
                "AppreciationProfesseur": "Des résultats corrects, que confirment les progrès du trimestre précédent. Gabrielle est volontaire et s'est investie avec sérieux. Il faudra persévérer avec une participation accrue en classe dès le début de l'année prochaine pour consolider les résultats."
              },
              {
                "MatiereBulletinLibelle": "Physique-Chimie Spécialité",
                "MoyenneduCandidat": "11,36",
                "MoyenneclasseCandidat": "11,81",
                "MoyenneBasseClasseduCandidat": "8,29",
                "MoyenneHauteClasseduCandidat": "16,66",
                "TypedeSaisieCode": 1,
                "AppreciationProfesseur": "Travail sérieux, assez bon ensemble."
              }
            ]
          },
          {
            "TrimestreLibelle": "Premier trimestre",
            "BulletinsScolairesParPeriode": [
              {
                "MatiereBulletinLibelle": "Sciences de la vie et de la Terre Spécialité",
                "MoyenneduCandidat": "15,81",
                "MoyenneclasseCandidat": "15,04",
                "MoyenneBasseClasseduCandidat": "10,00",
                "MoyenneHauteClasseduCandidat": "19,00",
                "TypedeSaisieCode": 1,
                "AppreciationProfesseur": "Bon trimestre, Gabrielle est une élève sérieuse. Le travail est régulier et l'analyse pertinente."
              },
              {
                "MatiereBulletinLibelle": "Physique-Chimie Spécialité",
                "MoyenneduCandidat": "11,63",
                "MoyenneclasseCandidat": "11,96",
                "MoyenneBasseClasseduCandidat": "9,25",
                "MoyenneHauteClasseduCandidat": "15,98",
                "TypedeSaisieCode": 1,
                "AppreciationProfesseur": "Assez bon travail, continuez ainsi."
              },
              {
                "MatiereBulletinLibelle": "Français",
                "MoyenneduCandidat": "15,10",
                "MoyenneclasseCandidat": "11,95",
                "MoyenneBasseClasseduCandidat": "5,76",
                "MoyenneHauteClasseduCandidat": "15,14",
                "TypedeSaisieCode": 1,
                "AppreciationProfesseur": "C'est un trimestre très satisfaisant en français. Gabrielle a bien compris les attentes de la matière et son travail régulier et réfléchi lui a permis de progresser et d'obtenir de très bons résultats. Qu'elle persévère dans cette voie."
              },
              {
                "MatiereBulletinLibelle": "Mathématiques Spécialité",
                "MoyenneduCandidat": "10,77",
                "MoyenneclasseCandidat": "11,57",
                "MoyenneBasseClasseduCandidat": "5,69",
                "MoyenneHauteClasseduCandidat": "17,91",
                "TypedeSaisieCode": 1,
                "AppreciationProfesseur": "Un ensemble juste et des lacunes. Vous devez persévérez dans les efforts engagés en privilégiant la régularité et la rigueur de l'investissement. N'hésitez pas également à participer. Des progrès sont nécessaires, vous en êtes capable !"
              },
              {
                "MatiereBulletinLibelle": "Langue vivante A",
                "MoyenneduCandidat": "17,10",
                "MoyenneclasseCandidat": "14,22",
                "MoyenneBasseClasseduCandidat": "10,10",
                "MoyenneHauteClasseduCandidat": "18,50",
                "TypedeSaisieCode": 1,
                "AppreciationProfesseur": "Très bon trimestre. Gabrielle est une élève sérieuse qui a un bon niveau de langue. Elle doit poursuivre ainsi en participant davantage !"
              }
            ]
          }
        ]
      }
    },
    {
      "AnneeLibelle": "2025-2026",
      "BulletinsScolairesAnnee": {
        "SerieLibelle": "Série Générale",
        "BulletinsScolairesSeries": [
          {
            "TrimestreLibelle": "Second trimestre",
            "BulletinsScolairesParPeriode": [
              {
                "MatiereBulletinLibelle": "Mathématiques Spécialité",
                "MoyenneduCandidat": "12,64",
                "MoyenneclasseCandidat": "12,08",
                "MoyenneBasseClasseduCandidat": "3,41",
                "MoyenneHauteClasseduCandidat": "19,03",
                "TypedeSaisieCode": 1,
                "AppreciationProfesseur": "Assez bon trimestre. De nets progrès avec une réflexion personnelle qui s'est approfondie. Les méthodologies sont également mieux suivies. Poursuivez dans cette dynamique efficace !"
              },
              {
                "MatiereBulletinLibelle": "Physique-Chimie Spécialité",
                "MoyenneduCandidat": "13,32",
                "MoyenneclasseCandidat": "13,04",
                "MoyenneBasseClasseduCandidat": "5,90",
                "MoyenneHauteClasseduCandidat": "17,53",
                "TypedeSaisieCode": 1,
                "AppreciationProfesseur": "Des résultats en retrait ce trimestre et en dessous de vos capacités : votre travail a manqué de régularité."
              },
              {
                "MatiereBulletinLibelle": "Langue vivante A",
                "MoyenneduCandidat": "13,31",
                "MoyenneclasseCandidat": "13,64",
                "MoyenneBasseClasseduCandidat": "9,16",
                "MoyenneHauteClasseduCandidat": "17,98",
                "TypedeSaisieCode": 1,
                "AppreciationProfesseur": "Très bon trimestre. Travail toujours sérieux avec une participation positive en classe. Continuez ainsi!\n"
              },
              {
                "MatiereBulletinLibelle": "Philosophie",
                "MoyenneduCandidat": "13,75",
                "MoyenneclasseCandidat": "13,68",
                "MoyenneBasseClasseduCandidat": "8,57",
                "MoyenneHauteClasseduCandidat": "18,29",
                "TypedeSaisieCode": 1,
                "AppreciationProfesseur": "Un très bon trimestre riche en progrès. Un ensemble très satisfaisant et très prometteur pour la suite de l'année et au-delà."
              }
            ]
          },
          {
            "TrimestreLibelle": "Premier trimestre",
            "BulletinsScolairesParPeriode": [
              {
                "MatiereBulletinLibelle": "Mathématiques Spécialité",
                "MoyenneduCandidat": "10,90",
                "MoyenneclasseCandidat": "11,15",
                "MoyenneBasseClasseduCandidat": "5,87",
                "MoyenneHauteClasseduCandidat": "18,90",
                "TypedeSaisieCode": 1,
                "AppreciationProfesseur": "Trimestre convenable en deçà de votre potentiel. Un apprentissage plus soutenu des cours s'impose afin d'atteindre les progrès dont vous êtes capable."
              },
              {
                "MatiereBulletinLibelle": "Philosophie",
                "MoyenneduCandidat": "15,28",
                "MoyenneclasseCandidat": "14,50",
                "MoyenneBasseClasseduCandidat": "11,44",
                "MoyenneHauteClasseduCandidat": "18,00",
                "TypedeSaisieCode": 1,
                "AppreciationProfesseur": "Un excellent trimestre porté avec éclat par Gabrielle. Il faut continuer ainsi, c'est extrêmement prometteur."
              },
              {
                "MatiereBulletinLibelle": "Langue vivante A",
                "MoyenneduCandidat": "16,31",
                "MoyenneclasseCandidat": "14,39",
                "MoyenneBasseClasseduCandidat": "9,38",
                "MoyenneHauteClasseduCandidat": "19,88",
                "TypedeSaisieCode": 1,
                "AppreciationProfesseur": "Très bon trimestre. Un travail de belle qualité. Élève sérieuse et motivée."
              },
              {
                "MatiereBulletinLibelle": "Physique-Chimie Spécialité",
                "MoyenneduCandidat": "14,66",
                "MoyenneclasseCandidat": "13,72",
                "MoyenneBasseClasseduCandidat": "8,63",
                "MoyenneHauteClasseduCandidat": "18,45",
                "TypedeSaisieCode": 1,
                "AppreciationProfesseur": "Un bon trimestre dans l'ensemble fruit d'un travail efficace mais qui manque de régularité. N'hésitez pas à participer davantage en classe et à être plus rigoureuse dans vos raisonnements pour pouvoir progresser."
              }
            ]
          }
        ]
      }
    }
  ],
  "FicheAvenir": {
    "NiveauClasseCode": 5
  },
  "AppreciationsEnseignantsFicheAvenir": [
    {
      "MatiereFicheAvenirLibelle": "Philosophie",
      "MatiereFicheAvenirLibelleBCN": "PHILOSOPHIE",
      "AppreciationFicheAvenir": "Un(e) élève appliqué(e) qui a fourni toutes les preuves de grandes aptitudes à la conceptualisation et à l'analyse. L'acquisition des méthodes est très satisfaisant et augure de grandes réalisations dans le supérieur. Le potentiel est qualitatif. Je recommande vivement l'élève à l'attention de ses premiers choix sur parcoursup."
    },
    {
      "MatiereFicheAvenirLibelle": "Langue vivante A",
      "MatiereFicheAvenirLibelleBCN": "LANGUE VIVANTE 1",
      "AppreciationFicheAvenir": "Un très bon niveau de compétence. L'élève fait preuve d'une grande aisance, notamment à l'oral, et sait mobiliser ses connaissances culturelles pour enrichir son propos. La rigueur méthodologique et la maturité démontrées garantissent une excellente adaptation à l'enseignement supérieur.\nNiveau C1 (IELTS) validé le 08/10/2025."
    },
    {
      "MatiereFicheAvenirLibelle": "Mathématiques Spécialité",
      "MatiereFicheAvenirLibelleBCN": "MATHEMATIQUES",
      "AppreciationFicheAvenir": "Assez bon niveau. Des progrès notoires ont vu le jour. Avec un travail personnel plus approfondi, la poursuite des progrès est très probable. Raisonnements clairs et structurés. Apte à suivre un cursus scientifique avec une part importante de mathématiques."
    },
    {
      "MatiereFicheAvenirLibelle": "Physique-Chimie Spécialité",
      "MatiereFicheAvenirLibelleBCN": "PHYSIQUE-CHIMIE",
      "AppreciationFicheAvenir": "Dans une classe de très bon niveau, cette élève a fourni tout au long de l'année un travail personnel efficace et a fait preuve de belles capacités scientifiques. Sa participation en classe a été active et positive. Elle sait mobiliser ses connaissances et ses savoirs faire à bon escient. Ses acquis en sciences physiques et chimiques sont désormais très solides et lui permettent d'envisager des études scientifiques très sélectives."
    }
  ],
  "Baccalaureat": {
    "EDSScolaritePremiere1LibelleBCN": "MATHEMATIQUES",
    "EDSScolaritePremiere2LibelleBCN": "PHYSIQUE-CHIMIE",
    "EDSScolaritePremiere3LibelleBCN": "SCIENCES DE LA VIE ET DE LA TERRE",
    "EDSScolariteTerminale1Libelle": "Mathématiques Spécialité",
    "EDSScolariteTerminale2Libelle": "Physique-Chimie Spécialité",
    "EDSScolaritePremiere1Libelle": "Mathématiques Spécialité",
    "EDSScolaritePremiere2Libelle": "Physique-Chimie Spécialité",
    "EDSScolaritePremiere3Libelle": "Sciences de la vie et de la Terre Spécialité"
  },
  "NotesBaccalaureat": [
    {
      "EpreuveLibelle": "Mathématiques"
    },
    {
      "EpreuveLibelle": "Physique-Chimie"
    },
    {
      "EpreuveLibelle": "Français écrit",
      "NoteEpreuve": "14,0"
    },
    {
      "EpreuveLibelle": "Français oral",
      "NoteEpreuve": "13,0"
    },
    {
      "EpreuveLibelle": "Sciences de la Vie et de la Terre  (EDS suivi uniquement en Première)",
      "NoteEpreuve": "15,7"
    }
  ],
  "DonneesVoeux": {
    "LettreDeMotivation": "<br /> Madame, Monsieur,<br /> <br /> Après 10 années passionnantes en Asie en lycées internationaux jusqu’en 2018, je suis actuellement élève en Terminale à Saint Jean Hulst à Versailles. Vivement intéressée par votre formation d’excellence, je vous adresse ma candidature en classe préparatoire BCPST.   <br /> <br /> Je pense avoir le profil requis, grâce à mon dossier scolaire solide et équilibré. J’aime la physique-chimie et les sciences de la vie et de la Terre, qui font écho à mon enfance marquée par l’amour de la terre et du vivant, étant d’une famille d’agriculteurs; je me suis intéressée aux techniques avancées d’une agriculture performante, mais respectueuse de l’environnement, et j’ai développé une bonne capacité d’observation et d’analyse scientifique, en particulier lors de mes stages. Ayant une personnalité rigoureuse et organisée, j’apprécie également les mathématiques. Je dispose d’excellentes capacités rédactionnelles et d’un bon esprit de synthèse. Enfin, mes expériences à l’étranger m’ont donné de l’aisance en anglais (niveau C1 IELTS), en espagnol, et en japonais.<br /> <br /> De plus, mes engagements sportifs et musicaux m’ont appris le sens de l’effort, la rigueur, la persévérance, et l’esprit d’équipe, qualités essentielles pour réussir en prépa. <br /> <br /> Les témoignages d’anciens élèves rencontrés cette année m’ont convaincue que votre formation me permettra de travailler efficacement, en vue d’intégrer une école d’ingénieur en agronomie prestigieuse. <br /> <br /> ​​​​​​​En espérant avoir retenu votre attention."
  }
}