{
  "exportDeDonnees": {
    "etablissementCode": "0750663N",
    "modeleCode": 42807,
    "exportCandidats": [
      {
        "formationCode": 8994,
        "candidats": [
          {
            "DonneesCandidats": {
              "NumeroDossierCandidat": 1356424,
              "NomCandidat": "SECK",
              "PrenomCandidat": "Soukeyna",
              "DateNaissance": "24/08/2006"
            },
            "Scolarite": [
              {
                "AnneeScolaireLibelle": "2024-2025",
                "ScolariteFrancaiseLibelle": "Scolarité étrangère",
                "NiveauEtudeLibelle": "Terminale",
                "TypeFormationLibelle": "Terminale",
                "TypeClasseLibelle": "Technologique",
                "NomEtablissementOrigine": "Lycée Francois Xavier Ndione de Thies",
                "CommuneEtablissementOrigineLibelle": "Thiès",
                "PaysEtablissementorigineLibelle": "Sénégal"
              },
              {
                "ScolariteFrancaiseLibelle": "Scolarité étrangère"
              }
            ],
            "BulletinsScolaires": [],
            "FicheAvenir": {},
            "AppreciationsEnseignantsFicheAvenir": [],
            "Baccalaureat": {},
            "NotesBaccalaureat": []
          }
        ]
      }
    ]
  }
}